odoo/addons/l10n_br_portal/README.rst
odoo/addons/l10n_br_portal/__init__.py
odoo/addons/l10n_br_portal/__manifest__.py
odoo/addons/l10n_br_portal/controllers/__init__.py
odoo/addons/l10n_br_portal/controllers/portal.py
odoo/addons/l10n_br_portal/demo/res_users_demo.xml
odoo/addons/l10n_br_portal/i18n/l10n_br_portal.pot
odoo/addons/l10n_br_portal/i18n/pt_BR.po
odoo/addons/l10n_br_portal/models/__init__.py
odoo/addons/l10n_br_portal/models/res_partner.py
odoo/addons/l10n_br_portal/readme/CONFIGURE.rst
odoo/addons/l10n_br_portal/readme/CONTRIBUTORS.rst
odoo/addons/l10n_br_portal/readme/DESCRIPTION.rst
odoo/addons/l10n_br_portal/readme/INSTALL.rst
odoo/addons/l10n_br_portal/readme/ROADMAP.rst
odoo/addons/l10n_br_portal/readme/USAGE.rst
odoo/addons/l10n_br_portal/static/description/icon.png
odoo/addons/l10n_br_portal/static/description/index.html
odoo/addons/l10n_br_portal/static/description/screenshot1.png
odoo/addons/l10n_br_portal/static/lib/cleave/cleave.min.js
odoo/addons/l10n_br_portal/static/src/js/l10n_br_portal.js
odoo/addons/l10n_br_portal/static/src/js/l10n_br_portal_tour.js
odoo/addons/l10n_br_portal/tests/__init__.py
odoo/addons/l10n_br_portal/tests/test_load_process.py
odoo/addons/l10n_br_portal/views/assets.xml
odoo/addons/l10n_br_portal/views/portal_templates.xml
odoo14_addon_l10n_br_portal-14.0.2.0.3.dist-info/METADATA
odoo14_addon_l10n_br_portal-14.0.2.0.3.dist-info/WHEEL
odoo14_addon_l10n_br_portal-14.0.2.0.3.dist-info/top_level.txt
odoo14_addon_l10n_br_portal-14.0.2.0.3.dist-info/RECORD
